transformative/__init__.py
transformative/conversion/__init__.py
transformative/conversion/autoconvert.py
transformative/conversion/decorator.py
transformative/conversion/function_creation.py
transformative/conversion/namer.py
transformative/conversion/searcher.py
transformative/conversion/test_runner.py
transformative/conversion/types.py
transformative/utils/__init__.py
transformative/utils/code_wrangling.py
transformative/utils/litellm_tools.py
transformative/utils/print_utils.py
transformative/utils/str_utils.py
transformative/utils/type_analysis.py
transformative-0.0.4.dist-info/LICENSE
transformative-0.0.4.dist-info/METADATA
transformative-0.0.4.dist-info/WHEEL
transformative-0.0.4.dist-info/top_level.txt
transformative-0.0.4.dist-info/RECORD
