Metadata-Version: 2.2
Name: transformative
Version: 0.0.4
Summary: Convert any X to any Y automatically using AI-powered code generation
Author-email: Andrew Keenan Richardson <richardson.andrew@gmail.com>
Project-URL: Homepage, https://github.com/qemqemqem/transformative
Project-URL: Bug Tracker, https://github.com/qemqemqem/transformative/issues
Classifier: Programming Language :: Python :: 3
Classifier: License :: OSI Approved :: MIT License
Classifier: Operating System :: OS Independent
Requires-Python: >=3.9
License-File: LICENSE
Requires-Dist: litellm>=1.0.0
Requires-Dist: instructor>=0.4.0
Requires-Dist: openai>=1.0.0
Requires-Dist: diskcache>=5.6.0
Requires-Dist: pytest>=7.0.0
Requires-Dist: pydantic>=2.10.0
Requires-Dist: aider-chat>=0.18.0
